{
  "id": "7ac1223c2e308f3430729d733b055a21",
  "position": "3r1rk1/pp3p2/3bpn1R/3pN3/Nn1P4/8/PPP2PP1/R2QK3 b Q - 0 16",
  "best_move": "g8g7",
  "played_move": "f6e4",
  "eval_diff": 9389,
  "themes": [
    "mistake"
  ],
  "turn_color": "black",
  "turn_player": "Meea",
  "game": {
    "id": "725348221",
    "white": "skarlman",
    "black": "Meea",
    "timestamp": 1731152170,
    "url": "https://www.chess.com/analysis/game/daily/725348221?tab=analysis&move=30",
    "pgn": "[Event \"Let's Play\"]\n[Site \"Chess.com\"]\n[Date \"2024.11.05\"]\n[Round \"-\"]\n[White \"skarlman\"]\n[Black \"Meea\"]\n[Result \"1-0\"]\n[CurrentPosition \"3r1rk1/pp3p2/3bp2R/3pN1Q1/Nn1P4/8/PPP2PP1/R3K3 b Q - 0 18\"]\n[Timezone \"UTC\"]\n[ECO \"D02\"]\n[ECOUrl \"https://www.chess.com/openings/Queens-Pawn-Opening-Zukertort-Variation-2...e6-3.Bf4-Nf6\"]\n[UTCDate \"2024.11.05\"]\n[UTCTime \"17:38:45\"]\n[WhiteElo \"962\"]\n[BlackElo \"570\"]\n[TimeControl \"1/259200\"]\n[Termination \"skarlman won by checkmate\"]\n[StartTime \"17:38:45\"]\n[EndDate \"2024.11.09\"]\n[EndTime \"11:36:10\"]\n[Link \"https://www.chess.com/game/daily/725348221\"]\n\n1. d4 {[%clk 60:40:23]} 1... d5 {[%clk 71:31:34]} 2. Bf4 {[%clk 71:41:01]} 2... e6 {[%clk 70:03:10]} 3. Nf3 {[%clk 66:47:42]} 3... Nf6 {[%clk 65:52:32]} 4. Nc3 {[%clk 62:13:12]} 4... Bd6 {[%clk 71:40:48]} 5. e3 {[%clk 70:52:12]} 5... O-O {[%clk 71:59:32]} 6. Ne5 {[%clk 71:57:10]} 6... Nc6 {[%clk 64:07:02]} 7. Bd3 {[%clk 56:54:29]} 7... Bd7 {[%clk 61:07:07]} 8. Bg5 {[%clk 70:58:11]} 8... Nb4 {[%clk 68:59:05]} 9. Bxh7+ {[%clk 71:33:38]} 9... Nxh7 {[%clk 71:48:22]} 10. Bxd8 {[%clk 71:55:38]} 10... Raxd8 {[%clk 71:55:22]} 11. h4 {[%clk 71:53:47]} 11... Ba4 {[%clk 61:37:06]} 12. Nxa4 {[%clk 69:39:57]} 12... Nf6 {[%clk 71:54:13]} 13. h5 {[%clk 71:54:48]} 13... c5 {[%clk 71:48:26]} 14. h6 {[%clk 71:59:13]} 14... cxd4 {[%clk 71:56:29]} 15. exd4 {[%clk 71:45:42]} 15... gxh6 {[%clk 71:54:21]} 16. Rxh6 {[%clk 71:38:33]} 16... Ne4 {[%clk 71:53:26]} 17. Qg4+ {[%clk 71:56:28]} 17... Ng5 {[%clk 71:54:30]} 18. Qxg5# {[%clk 71:37:26]} 1-0\n",
    "move_number": 16
  }
}